{
  "lstorms": {
    "floods": {},
    "hurricanes": {
      "Florida_Keys": {
        "overview": "",
        "landfall": {
          "cat": "",
          "date": "",
          "loc": "",
          "windspeed": "",
          "pressure": ""
        },
        "max": {
          "catMax": "",
          "windspeedMax": "",
          "pressureMax": ""
        },
        
        "impact": {
          "casualties": "",
          "injuries": "",
          "homeDestroyed": "",
          "cost": ""
        },
        "facts": "",
        "img1": "",
        "img2": ""
      },
      "Galveston": {
        "overview": "",
        "landfall": {
          "cat": "",
          "date": "",
          "loc": "",
          "windspeed": "",
          "pressure": ""
        },
        "max": {
          "catMax": "",
          "windspeedMax": "",
          "pressureMax": ""
        },
        
        "impact": {
          "casualties": "",
          "injuries": "",
          "homeDestroyed": "",
          "cost": ""
        },
        "facts": "",
        "img1": "",
        "img2": ""
      },
      "Harvey": {
        "overview": "",
        "landfall": {
          "cat": "",
          "date": "",
          "loc": "",
          "windspeed": "",
          "pressure": ""
        },
        "max": {
          "catMax": "",
          "windspeedMax": "",
          "pressureMax": ""
        },
        
        "impact": {
          "casualties": "",
          "injuries": "",
          "homeDestroyed": "",
          "cost": ""
        },
        "facts": "",
        "img1": "",
        "img2": ""
      },
      "Ian": {
        "overview": "",
        "landfall": {
          "cat": "",
          "date": "",
          "loc": "",
          "windspeed": "",
          "pressure": ""
        },
        "max": {
          "catMax": "",
          "windspeedMax": "",
          "pressureMax": ""
        },
        
        "impact": {
          "casualties": "",
          "injuries": "",
          "homeDestroyed": "",
          "cost": ""
        },
        "facts": "",
        "img1": "",
        "img2": ""
      },
      "Katrina": {
        "overview": "",
        "landfall": {
          "cat": "",
          "date": "",
          "loc": "",
          "windspeed": "",
          "pressure": ""
        },
        "max": {
          "catMax": "",
          "windspeedMax": "",
          "pressureMax": ""
        },
        
        "impact": {
          "casualties": "",
          "injuries": "",
          "homeDestroyed": "",
          "cost": ""
        },
        "facts": "",
        "img1": "",
        "img2": ""
      },
      "Patricia": {
        "overview": "",
        "landfall": {
          "cat": "",
          "date": "",
          "loc": "",
          "windspeed": "",
          "pressure": ""
        },
        "max": {
          "catMax": "",
          "windspeedMax": "",
          "pressureMax": ""
        },
        
        "impact": {
          "casualties": "",
          "injuries": "",
          "homeDestroyed": "",
          "cost": ""
        },
        "facts": "",
        "img1": "",
        "img2": ""
      },
      "Sandy": {
        "overview": "",
        "landfall": {
          "cat": "",
          "date": "",
          "loc": "",
          "windspeed": "",
          "pressure": ""
        },
        "max": {
          "catMax": "",
          "windspeedMax": "",
          "pressureMax": ""
        },
        
        "impact": {
          "casualties": "",
          "injuries": "",
          "homeDestroyed": "",
          "cost": ""
        },
        "facts": "",
        "img1": "",
        "img2": ""
      }
    },
    "snow": {
      "Great Blizzard": {
        "overview": "",
        "date": "",
        "snowAmountIN": "",
        "impact": {
          "cost": "",
          "powerOutages": ""
        },
        "facts": ""
      },
      "Blizzard of '78": {
        "overview": "",
        "date": "",
        "snowAmountIN": "",
        "impact": {
          "cost": "",
          "powerOutages": ""
        },
        "facts": ""
      },
      "Blizzard of the Century": {
        "overview": "",
        "date": "",
        "snowAmountIN": "",
        "impact": {
          "cost": "",
          "powerOutages": ""
        },
        "facts": ""
      }
    },
    "tornadoes": {
      "Tri-State": {
        "overview": "",
        "date": "",
        "loc": "",
        "duration": "",
        "windspeed": "",
        "ef-rating": "",
        "impact": {
          "casualties": "",
          "injuries": "",
          "homeDestroyed": "",
          "cost": ""
        },
        "facts": ""
      },
      "2011 Super Outbreak": {
        "overview": "",
        "date": "",
        "loc": "",
        "duration": "",
        "windspeed": "",
        "ef-rating": "",
        "impact": {
          "casualties": "",
          "injuries": "",
          "homeDestroyed": "",
          "cost": ""
        },
        "facts": ""
      },
      "El-Reno, Oklahoma": {
        "overview": "",
        "date": "",
        "loc": "",
        "duration": "",
        "windspeed": "",
        "ef-rating": "",
        "impact": {
          "casualties": "",
          "injuries": "",
          "homeDestroyed": "",
          "cost": ""
        },
        "facts": ""
      }
    }
  }
}
